setup.cfg
setup.py
ghplots/__init__.py
github_plots.egg-info/PKG-INFO
github_plots.egg-info/SOURCES.txt
github_plots.egg-info/dependency_links.txt
github_plots.egg-info/entry_points.txt
github_plots.egg-info/not-zip-safe
github_plots.egg-info/requires.txt
github_plots.egg-info/top_level.txt