Metadata-Version: 1.0
Name: github-plots
Version: 0.1
Summary: Alternative plots from GitHub stats.
Home-page: http://github.com/cartlogic/github-plots
Author: Scott Torborg
Author-email: scott@cartlogic.com
License: MIT
Keywords: git github stats plotting version control
Platform: UNKNOWN
Classifier: License :: OSI Approved :: MIT License
Classifier: Programming Language :: Python :: 2.7
